LICENSE
MANIFEST.in
README.md
pyproject.toml
setup.py
./setup.py
./examples/demo.py
./pragmastat/__init__.py
./pragmastat/_constants.py
./pragmastat/estimators.py
./pragmastat/fast_center.py
./pragmastat/fast_shift.py
./pragmastat/fast_spread.py
./pragmastat/pairwise_margin.py
./pragmastat/rng.py
./pragmastat/xoshiro256.py
./pragmastat/distributions/__init__.py
./pragmastat/distributions/additive.py
./pragmastat/distributions/distribution.py
./pragmastat/distributions/exp.py
./pragmastat/distributions/multiplic.py
./pragmastat/distributions/power.py
./pragmastat/distributions/uniform.py
./tests/test_invariance.py
./tests/test_performance.py
./tests/test_reference.py
examples/demo.py
pragmastat/__init__.py
pragmastat/_constants.py
pragmastat/estimators.py
pragmastat/fast_center.py
pragmastat/fast_shift.py
pragmastat/fast_spread.py
pragmastat/pairwise_margin.py
pragmastat/rng.py
pragmastat/xoshiro256.py
pragmastat.egg-info/PKG-INFO
pragmastat.egg-info/SOURCES.txt
pragmastat.egg-info/dependency_links.txt
pragmastat.egg-info/requires.txt
pragmastat.egg-info/top_level.txt
pragmastat/distributions/__init__.py
pragmastat/distributions/additive.py
pragmastat/distributions/distribution.py
pragmastat/distributions/exp.py
pragmastat/distributions/multiplic.py
pragmastat/distributions/power.py
pragmastat/distributions/uniform.py
src/fast_center_c.c
src/fast_shift_c.c
src/fast_spread_c.c
tests/test_invariance.py
tests/test_performance.py
tests/test_reference.py