Metadata-Version: 2.4
Name: pragmastat
Version: 5.0.0
Summary: Pragmastat: Pragmatic Statistical Toolkit
Author: Andrey Akinshin
License-Expression: MIT
Project-URL: Homepage, https://pragmastat.dev
Project-URL: Repository, https://github.com/AndreyAkinshin/pragmastat
Project-URL: DOI, https://doi.org/10.5281/zenodo.17236778
Keywords: statistics
Requires-Python: >=3.8
License-File: LICENSE
Requires-Dist: numpy>=1.20
Dynamic: license-file
